data_augmentation/__init__.py
data_augmentation/img/__init__.py
data_augmentation/img/__main__.py
data_augmentation/img/generate_samples.py
data_augmentation/img/transformations.py
data_augmentation/img/utils.py
smh_data_augmentation-0.0.2.dist-info/LICENSE
smh_data_augmentation-0.0.2.dist-info/METADATA
smh_data_augmentation-0.0.2.dist-info/WHEEL
smh_data_augmentation-0.0.2.dist-info/top_level.txt
smh_data_augmentation-0.0.2.dist-info/RECORD
