Metadata-Version: 2.1
Name: smh-data-augmentation
Version: 0.0.2
Summary: A data augmentator package
Home-page: https://github.com/beeva-samuelmunoz/data_augmentator
Author: Samuel M.H.
Author-email: samuel.mh@gmail.com
License: UNKNOWN
Platform: UNKNOWN
Classifier: Programming Language :: Python :: 3
Classifier: Operating System :: OS Independent
Requires-Dist: scikit-image (>=0.14.2)
